simple_python_project_template/__init__.py
simple_python_project_template/__main__.py
simple_python_project_template/simple_python_project_template.py
simple_python_project_template-0.0.2.dist-info/LICENSE
simple_python_project_template-0.0.2.dist-info/LICENSE.txt
simple_python_project_template-0.0.2.dist-info/METADATA
simple_python_project_template-0.0.2.dist-info/WHEEL
simple_python_project_template-0.0.2.dist-info/entry_points.txt
simple_python_project_template-0.0.2.dist-info/top_level.txt
simple_python_project_template-0.0.2.dist-info/RECORD
