Metadata-Version: 2.1
Name: simple-python-project-template
Version: 0.0.2
Summary: A simple Python project template.
Home-page: https://github.com/hreikin/simple-python-project-template
Author: user
Author-email: user@example.com
License: MIT
Platform: UNKNOWN
Classifier: License :: OSI Approved :: MIT License
Classifier: Programming Language :: Python :: 3
Classifier: Programming Language :: Python :: 3.7
License-File: LICENSE
License-File: LICENSE.txt
